{
  "$schema": "https://developer.microsoft.com/json-schemas/spfx-build/package-solution.schema.json",
  "solution": {
    "name": "bharath-client-side-solution",
    "id": "578bc9e8-63a4-477a-b0ec-6731f159129c",
    "version": "1.0.0.0",
    "includeClientSideAssets": true,
    "skipFeatureDeployment": true,
    "isDomainIsolated": false,
    "developer": {
      "name": "",
      "websiteUrl": "",
      "privacyUrl": "",
      "termsOfUseUrl": "",
      "mpnId": "Undefined-1.18.1"
    },
    "metadata": {
      "shortDescription": {
        "default": "bharath description"
      },
      "longDescription": {
        "default": "bharath description"
      },
      "screenshotPaths": [],
      "videoUrl": "",
      "categories": []
    },
    "features": [
      {
        "title": "bharath Feature",
        "description": "The feature that activates elements of the bharath solution.",
        "id": "6dd2366a-c4e6-40c7-bdd3-24bf19e8a14d",
        "version": "1.0.0.0"
      }
    ]
  },
  "paths": {
    "zippedPackage": "solution/bharath.sppkg"
  }
}
